LICENSE
MANIFEST.in
README
README.rst
setup.cfg
setup.py
src/decafjoe_safe.egg-info/PKG-INFO
src/decafjoe_safe.egg-info/SOURCES.txt
src/decafjoe_safe.egg-info/dependency_links.txt
src/decafjoe_safe.egg-info/entry_points.txt
src/decafjoe_safe.egg-info/not-zip-safe
src/decafjoe_safe.egg-info/requires.txt
src/decafjoe_safe.egg-info/top_level.txt
src/safe/__init__.py
src/safe/app.py
src/safe/clip.py
src/safe/compat.py
src/safe/db.py
src/safe/ec.py
src/safe/gpg.py
src/safe/model.py
src/safe/sgen.py
src/safe/srm.py
src/safe/util.py
src/safe/cmd/__init__.py
src/safe/cmd/copy.py
src/safe/cmd/init.py
src/safe/cmd/ipy.py
src/safe/cmd/print_.py
src/safe/cmd/shell.py
src/safe/cmd/drop/__init__.py
src/safe/cmd/drop/account.py
src/safe/cmd/drop/policy.py
src/safe/cmd/gen/__init__.py
src/safe/cmd/gen/bare.py
src/safe/cmd/gen/per_policy.py
src/safe/cmd/list/__init__.py
src/safe/cmd/list/account.py
src/safe/cmd/list/policy.py
src/safe/cmd/list/util.py
src/safe/cmd/new/__init__.py
src/safe/cmd/new/account.py
src/safe/cmd/new/policy.py
src/safe/cmd/update/__init__.py
src/safe/cmd/update/account.py
src/safe/cmd/update/policy.py
src/safe/form/__init__.py
src/safe/form/account.py
src/safe/form/policy.py